{
  "generated_at": "2026-04-24T06:12:16.256848+00:00",
  "start_date": "2026-04-24",
  "num_days": 3,
  "games_per_date": {
    "2026-04-24": 14,
    "2026-04-25": 15,
    "2026-04-26": 15
  },
  "entries": [
    {
      "date": "2026-04-24",
      "cron": "1 8 24 4 *",
      "et_time": "4:01 ET"
    },
    {
      "date": "2026-04-24",
      "cron": "57 10 24 4 *",
      "et_time": "6:57 ET"
    },
    {
      "date": "2026-04-24",
      "cron": "10 21 24 4 *",
      "et_time": "17:10 ET"
    },
    {
      "date": "2026-04-24",
      "cron": "35 21 24 4 *",
      "et_time": "17:35 ET"
    },
    {
      "date": "2026-04-24",
      "cron": "10 22 24 4 *",
      "et_time": "18:10 ET"
    },
    {
      "date": "2026-04-24",
      "cron": "35 22 24 4 *",
      "et_time": "18:35 ET"
    },
    {
      "date": "2026-04-25",
      "cron": "1 8 25 4 *",
      "et_time": "4:01 ET"
    },
    {
      "date": "2026-04-25",
      "cron": "45 16 25 4 *",
      "et_time": "12:45 ET"
    },
    {
      "date": "2026-04-25",
      "cron": "37 17 25 4 *",
      "et_time": "13:37 ET"
    },
    {
      "date": "2026-04-25",
      "cron": "35 18 25 4 *",
      "et_time": "14:35 ET"
    },
    {
      "date": "2026-04-25",
      "cron": "35 20 25 4 *",
      "et_time": "16:35 ET"
    },
    {
      "date": "2026-04-25",
      "cron": "35 21 25 4 *",
      "et_time": "17:35 ET"
    },
    {
      "date": "2026-04-26",
      "cron": "1 8 26 4 *",
      "et_time": "4:01 ET"
    },
    {
      "date": "2026-04-26",
      "cron": "5 16 26 4 *",
      "et_time": "12:05 ET"
    },
    {
      "date": "2026-04-26",
      "cron": "40 16 26 4 *",
      "et_time": "12:40 ET"
    },
    {
      "date": "2026-04-26",
      "cron": "5 17 26 4 *",
      "et_time": "13:05 ET"
    },
    {
      "date": "2026-04-26",
      "cron": "35 18 26 4 *",
      "et_time": "14:35 ET"
    },
    {
      "date": "2026-04-26",
      "cron": "12 20 26 4 *",
      "et_time": "16:12 ET"
    },
    {
      "date": "2026-04-26",
      "cron": "50 21 26 4 *",
      "et_time": "17:50 ET"
    }
  ]
}